dingtalk_sdk_gmdzy2010/__init__.py
dingtalk_sdk_gmdzy2010/authority_request.py
dingtalk_sdk_gmdzy2010/base_request.py
dingtalk_sdk_gmdzy2010/department_request.py
dingtalk_sdk_gmdzy2010/message_request.py
dingtalk_sdk_gmdzy2010/settings.py
dingtalk_sdk_gmdzy2010/user_request.py
dingtalk_sdk_gmdzy2010/utils.py
dingtalk_sdk_gmdzy2010-0.5.0.dist-info/DESCRIPTION.rst
dingtalk_sdk_gmdzy2010-0.5.0.dist-info/METADATA
dingtalk_sdk_gmdzy2010-0.5.0.dist-info/RECORD
dingtalk_sdk_gmdzy2010-0.5.0.dist-info/WHEEL
dingtalk_sdk_gmdzy2010-0.5.0.dist-info/metadata.json
dingtalk_sdk_gmdzy2010-0.5.0.dist-info/top_level.txt
