Metadata-Version: 2.0
Name: dingtalk-sdk-gmdzy2010
Version: 0.5.0
Summary: The non-official sdk of dingtalk
Home-page: https://github.com/gmdzy2010/dingtalk_sdk_gmdzy2010
Author: gmdzy2010
Author-email: gmdzy2010@126.com
License: MIT License
Keywords: dingtalk
Platform: UNKNOWN
Classifier: Programming Language :: Python :: 3
Classifier: Programming Language :: Python :: 3.4
Classifier: Programming Language :: Python :: 3.5
Classifier: Programming Language :: Python :: 3.6
Classifier: License :: OSI Approved :: MIT License
Classifier: Operating System :: OS Independent
